unsplash_rand_downloader/__init__.py
unsplash_rand_downloader/__main__.py
unsplash_rand_downloader/_downloader.py
unsplash_rand_downloader-1.0.0.dist-info/LICENSE
unsplash_rand_downloader-1.0.0.dist-info/METADATA
unsplash_rand_downloader-1.0.0.dist-info/WHEEL
unsplash_rand_downloader-1.0.0.dist-info/top_level.txt
unsplash_rand_downloader-1.0.0.dist-info/RECORD
