Metadata-Version: 2.1
Name: unsplash-rand-downloader
Version: 1.0.0
Summary: Python Unsplash random image downloader manager.
Home-page: https://github.com/J-Rios/unsplash_rand_downloader
Author: Jose Miguel Rios Rubio
Author-email: jrios.github@gmail.com
License: MIT
Keywords: unsplash,random,image
Platform: UNKNOWN
Classifier: Development Status :: 4 - Beta
Classifier: Intended Audience :: Developers
Classifier: License :: OSI Approved :: MIT License
Classifier: Topic :: Software Development :: Libraries :: Python Modules
Requires-Dist: python-unsplash
Requires-Dist: requests
